chimera_client/__init__.py
chimera_client/environ.py
chimera_client/reader.py
chimera_client/schema.py
chimera_client/writer.py
chimera_client-0.0.2.dist-info/METADATA
chimera_client-0.0.2.dist-info/WHEEL
chimera_client-0.0.2.dist-info/top_level.txt
chimera_client-0.0.2.dist-info/RECORD
