Metadata-Version: 2.1
Name: chimera-client
Version: 0.0.2
Summary: Client for communication using chimera channels.
Home-page: https://gitlab.inspr.com/chimera/client
License: UNKNOWN
Platform: UNKNOWN
Requires-Dist: requests
Requires-Dist: avro-python3
Requires-Dist: confluent-kafka
